counter/updown/synchronousReset/updowncount.v
module updowncount(clk,reset,preset,mode,count);
   input reset,preset,clk,mode;
   output [4:0]count;
   reg [4:0]count;
   
    
     
   always@(posedge clk)
    begin
     
     if (reset)
       count <= 5'b00000;
     else if (preset)
       count <= 5'b11111;
     else if (mode == 1) //up counter
       count <= count + 1;
     else if (mode == 0) //down counter
       count <= count - 1;
    end
 endmodule

counter/updown/synchronousReset/testbench.v
module testbench;
  reg reset,preset,clk,mode;
  wire [4:0]count;
  
  updowncount D1 (clk,reset,preset,mode,count);
  
  initial clk=0;
  always clk = #2 ~clk;
  
  initial 
    begin
     $monitor($time,"clk=%b,reset=%b,preset=%b,mode=%b,count=%b",clk,reset,preset,mode,count);
     $dumpfile("waveform.vcd");
     $dumpvars(0,testbench);

     
     #0 reset = 1; preset = 0; mode = 1;
     #2 reset = 0; preset = 1; mode =0;
     #2 preset=1; mode=0;
     #1 preset = 0; 
     #10 mode=1;
     #1 reset =1;
     #50 $finish;
   end
endmodule

counter/updown/synchronousReset/waveform.vcd
$date
	Wed Dec 15 15:42:28 2021
$end
$version
	Icarus Verilog
$end
$timescale
	1s
$end
$scope module testbench $end
$var wire 5 ! count [4:0] $end
$var reg 1 " clk $end
$var reg 1 # mode $end
$var reg 1 $ preset $end
$var reg 1 % reset $end
$scope module D1 $end
$var wire 1 " clk $end
$var wire 1 # mode $end
$var wire 1 $ preset $end
$var wire 1 % reset $end
$var reg 5 & count [4:0] $end
$upscope $end
$upscope $end
$enddefinitions $end
#0
$dumpvars
bx &
1%
0$
1#
0"
bx !
$end
#2
b11111 !
b11111 &
0#
1$
0%
1"
#4
0"
#5
0$
#6
b11110 !
b11110 &
1"
#8
0"
#10
b11101 !
b11101 &
1"
#12
0"
#14
b11100 !
b11100 &
1"
#15
1#
#16
1%
0"
#18
b0 !
b0 &
1"
