16TO1using4TO1/assign/fourtooneAssign.v
module fourto1  (a,select,out);
  input [3:0]a;
  input [1:0]select;
  output out;
  
  assign out=a[select]; 
   
endmodule

module sixteento1 (A,S,Out);
  input [15:0] A;
  input [3:0] S;
  output Out;
  wire [3:0]O;
  
  fourto1 F1 (A[3:0],S[1:0],O[0]);
  fourto1 F2 (A[7:4],S[1:0],O[1]);
  fourto1 F3 (A[11:8],S[1:0],O[2]);  
  fourto1 F4 (A[15:12],S[1:0],O[3]);
  fourto1 F5 (O[3:0],S[3:2],Out);
  
endmodule

16TO1using4TO1/assign/testbench.v
module testbench;
  reg [15:0]A;
  reg [3:0]S;
  wire Result;
  
  sixteento1 S1 (A,S,Result);
  
  initial 
    begin
      $dumpfile("waveform.vcd");
      $dumpvars(0,testbench);
      $monitor($time,"A=%h,S=%h,Result=%b",A,S,Result);
      
      #5 A=16'ha067; S=4'h0;
      #5 S=4'h1;
      #5 S=4'h2;
      #5 S=4'h3;
      #5 S=4'h4;
      #5 S=4'h5;
      #5 S=4'h6;
      #5 S=4'h7;
      #5 S=4'h8;
      #5 S=4'h9;
      #5 S=4'ha;
      #5 $finish;
    end
endmodule

16TO1using4TO1/assign/waveform.vcd
$date
	Thu Sep 23 19:30:28 2021
$end
$version
	Icarus Verilog
$end
$timescale
	1s
$end
$scope module testbench $end
$var wire 1 ! Result $end
$var reg 16 " A [15:0] $end
$var reg 4 # S [3:0] $end
$scope module S1 $end
$var wire 16 $ A [15:0] $end
$var wire 4 % S [3:0] $end
$var wire 1 ! Out $end
$var wire 4 & O [3:0] $end
$scope module F1 $end
$var wire 4 ' a [3:0] $end
$var wire 2 ( select [1:0] $end
$var wire 1 ) out $end
$upscope $end
$scope module F2 $end
$var wire 4 * a [3:0] $end
$var wire 2 + select [1:0] $end
$var wire 1 , out $end
$upscope $end
$scope module F3 $end
$var wire 4 - a [3:0] $end
$var wire 2 . select [1:0] $end
$var wire 1 / out $end
$upscope $end
$scope module F4 $end
$var wire 4 0 a [3:0] $end
$var wire 2 1 select [1:0] $end
$var wire 1 2 out $end
$upscope $end
$scope module F5 $end
$var wire 4 3 a [3:0] $end
$var wire 2 4 select [1:0] $end
$var wire 1 ! out $end
$upscope $end
$upscope $end
$upscope $end
$enddefinitions $end
#0
$dumpvars
bx 4
bx 3
x2
bx 1
bx 0
x/
bx .
bx -
x,
bx +
bx *
x)
bx (
bx '
bx &
bx %
bx $
bx #
bx "
x!
$end
#5
1!
1)
b0 (
0,
b0 +
0/
b0 .
b1 &
b1 3
02
b0 1
b0 4
b111 '
b110 *
b0 -
b1010 0
b0 #
b0 %
b1010000001100111 "
b1010000001100111 $
#10
b1 (
1,
b1 +
b1 .
b1011 &
b1011 3
12
b1 1
b1 #
b1 %
#15
b10 (
b10 +
b10 .
b11 &
b11 3
02
b10 1
b10 #
b10 %
#20
0!
0)
b11 (
0,
b11 +
b11 .
b1000 &
b1000 3
12
b11 1
b11 #
b11 %
#25
1)
b0 (
b0 +
b0 .
b1 &
b1 3
02
b0 1
b1 4
b100 #
b100 %
#30
b1 (
1!
1,
b1 +
b1 .
b1011 &
b1011 3
12
b1 1
b101 #
b101 %
#35
b10 (
b10 +
b10 .
b11 &
b11 3
02
b10 1
b110 #
b110 %
