counter/ringCounter/ringcounter.v
module ringcounter(clk,init,count);
 input clk,init;
 output reg [3:0]count;
 
 always@(posedge clk)
   begin
    if (init)
      count <= 4'b1000;
    else
      begin
       count <= count<<1;
       count[0] <= count[3];
      end
   end
endmodule

counter/ringCounter/testbench.v
module testbench;
 reg clk,init;
 wire [3:0]count;
 
 ringcounter R1 (clk,init,count);
 
 initial clk = 0;
 always clk = #1 ~clk;
 
 
 initial 
  begin 
   $monitor($time,"clk=%b,init=%b,count=%b",clk,init,count);
   $dumpfile("waveform.vcd");
   $dumpvars(0,testbench);
   
   #0 init=1;
   #2 init=0;
   #100 $finish;
   
  end
 endmodule

counter/ringCounter/waveform.vcd
$date
	Wed Dec 15 15:48:04 2021
$end
$version
	Icarus Verilog
$end
$timescale
	1s
$end
$scope module testbench $end
$var wire 4 ! count [3:0] $end
$var reg 1 " clk $end
$var reg 1 # init $end
$scope module R1 $end
$var wire 1 " clk $end
$var wire 1 # init $end
$var reg 4 $ count [3:0] $end
$upscope $end
$upscope $end
$enddefinitions $end
#0
$dumpvars
bx $
1#
0"
bx !
$end
#1
b1000 !
b1000 $
1"
#2
0"
0#
#3
b1 !
b1 $
1"
#4
0"
#5
b10 !
b10 $
1"
#6
0"
#7
b100 !
b100 $
1"
#8
0"
#9
b1000 !
b1000 $
1"
#10
0"
#11
b1 !
b1 $
1"
#12
0"
#13
b10 !
b10 $
1"
#14
0"
#15
b100 !
b100 $
1"
#16
0"
#17
b1000 !
b1000 $
1"
#18
0"
#19
b1 !
b1 $
1"
#20
0"
#21
b10 !
b10 $
1"
#22
0"
#23
b100 !
b100 $
1"
#24
0"
#25
b1000 !
b1000 $
1"
#26
0"
#27
b1 !
b1 $
1"
#28
0"
#29
b10 !
b10 $
1"
#30
0"
#31
b100 !
b100 $
1"
#32
0"
#33
b1000 !
b1000 $
1"
#34
0"
#35
b1 !
b1 $
1"
#36
0"
#37
b10 !
b10 $
1"
#38
0"
#39
b100 !
b100 $
1"
#40
0"
#41
b1000 !
b1000 $
1"
#42
0"
#43
b1 !
b1 $
1"
#44
0"
#45
b10 !
b10 $
1"
#46
0"
#47
b100 !
b100 $
1"
#48
0"
#49
b1000 !
b1000 $
1"
#50
0"
#51
b1 !
b1 $
1"
#52
0"
#53
b10 !
b10 $
1"
#54
0"
#55
b100 !
b100 $
1"
#56
0"
#57
b1000 !
b1000 $
1"
#58
0"
#59
b1 !
b1 $
1"
#60
0"
#61
b10 !
b10 $
1"
#62
0"
#63
b100 !
b100 $
1"
#64
0"
#65
b1000 !
b1000 $
1"
#66
0"
#67
b1 !
b1 $
1"
#68
0"
#69
b10 !
b10 $
1"
#70
0"
#71
b100 !
b100 $
1"
#72
0"
#73
b1000 !
b1000 $
1"
#74
0"
#75
b1 !
b1 $
1"
#76
0"
#77
b10 !
b10 $
1"
#78
0"
#79
b100 !
b100 $
1"
#80
0"
#81
b1000 !
b1000 $
1"
#82
0"
#83
b1 !
b1 $
1"
#84
0"
#85
b10 !
b10 $
1"
#86
0"
#87
b100 !
b100 $
1"
#88
0"
#89
b1000 !
b1000 $
1"
#90
0"
#91
b1 !
b1 $
1"
#92
0"
#93
b10 !
b10 $
1"
#94
0"
#95
b100 !
b100 $
1"
#96
0"
#97
b1000 !
b1000 $
1"
#98
0"
#99
b1 !
b1 $
1"
#100
0"
#101
b10 !
b10 $
1"
