1to8Demux/if/oneto8demux.v
module oneto8demux(a,en,sel,out);
 input a;
 input en;
 input [2:0]sel;
 output reg [7:0]out;
 
 always@(*)
 begin
 if(en)
   begin 
     if (sel == 3'b000)
        out[0] = a;
     else if (sel == 3'b001)
        out[1] = a;
     else if (sel == 3'b010)
        out[2] = a;
     else if (sel == 3'b011)
        out[3] = a;
     else if (sel == 3'b100)
        out[4] = a;
     else if (sel == 3'b101)
        out[5] = a;
     else if (sel == 3'b110)
        out[6] = a;
     else if (sel == 3'b111)
        out[7] = a;
    end
  else 
     out = 8'bzzzzzzzz;
 end
endmodule

1to8Demux/if/testbench.v
module testbench;
 reg a;
 reg en;
 wire [7:0]out;
 reg [2:0]sel;
 
 oneto8demux D1 (a,en,sel,out);
 
 initial 
  begin 
   $monitor($time,"a=%b,en=%b,sel=%b,out=%b",a,en,sel,out);
   $dumpfile("waveform.vcd");
   $dumpvars(0,testbench);
   
   #0 en=0;a=1;sel=3'b001;
   #2 en=0;a=0;sel=3'b000;
   #4 en=1;a=1;sel=3'b000;
   #4 en=1;a=1;sel=3'b001;
   #4 en=1;a=0;sel=3'b010;
   #4 en=1;a=1;sel=3'b011;
   #4 en=1;a=1;sel=3'b100;
   #4 en=1;a=0;sel=3'b101;
   #4 en=1;a=1;sel=3'b110;
   #4 $finish;
  end
endmodule

1to8Demux/if/waveform.vcd
$date
	Tue Nov 23 22:40:58 2021
$end
$version
	Icarus Verilog
$end
$timescale
	1s
$end
$scope module testbench $end
$var wire 8 ! out [7:0] $end
$var reg 1 " a $end
$var reg 1 # en $end
$var reg 3 $ sel [2:0] $end
$scope module D1 $end
$var wire 1 " a $end
$var wire 1 # en $end
$var wire 3 % sel [2:0] $end
$var reg 8 & out [7:0] $end
$upscope $end
$upscope $end
$enddefinitions $end
#0
$dumpvars
b0z &
b1 %
b1 $
0#
1"
b0z !
$end
#2
b0 $
b0 %
0"
#6
b1 !
b1 &
1"
1#
#10
b11 !
b11 &
b1 $
b1 %
#14
b10 $
b10 %
0"
#18
b1011 !
b1011 &
b11 $
b11 %
1"
#22
b11011 !
b11011 &
b100 $
b100 %
#26
b101 $
b101 %
0"
#30
b1011011 !
b1011011 &
b110 $
b110 %
1"
