counter/up/upcount.v
module upcount(clk,reset,count);
   input reset,clk;
   output [4:0]count;
   reg [4:0]count;
   
    
     
   always@(posedge clk)
    begin
     
     if (reset)
       count <= 5'b00000;
     else
       count <= count + 1;
       
    end
 
 endmodule

counter/up/testbench.v
module testbench;
  reg reset,clk;
  wire [4:0]count;
  
  upcount D1 (clk,reset,count);
  
  initial clk=0;
  always clk = #1 ~clk;
  
  initial 
    begin
     $monitor($time,"clk=%b,reset=%b,count=%b",clk,reset,count);
     $dumpfile("waveform.vcd");
     $dumpvars(0,testbench);

     
     #0 reset = 1;
     #4 reset = 0;
     #50 $finish;
   end
endmodule

counter/up/waveform.vcd
$date
	Tue Dec 14 09:21:45 2021
$end
$version
	Icarus Verilog
$end
$timescale
	1s
$end
$scope module testbench $end
$var wire 5 ! count [4:0] $end
$var reg 1 " clk $end
$var reg 1 # reset $end
$scope module D1 $end
$var wire 1 " clk $end
$var wire 1 # reset $end
$var reg 5 $ count [4:0] $end
$upscope $end
$upscope $end
$enddefinitions $end
#0
$dumpvars
bx $
1#
0"
bx !
$end
#1
b0 !
b0 $
1"
#2
0"
#3
1"
#4
0"
0#
#5
b1 !
b1 $
1"
#6
0"
#7
b10 !
b10 $
1"
#8
0"
#9
b11 !
b11 $
1"
#10
0"
#11
b100 !
b100 $
1"
#12
0"
#13
b101 !
b101 $
1"
#14
0"
#15
b110 !
b110 $
1"
#16
0"
#17
b111 !
b111 $
1"
#18
0"
#19
b1000 !
b1000 $
1"
#20
0"
#21
b1001 !
b1001 $
1"
#22
0"
#23
b1010 !
b1010 $
1"
#24
0"
#25
b1011 !
b1011 $
1"
#26
0"
#27
b1100 !
b1100 $
1"
#28
0"
#29
b1101 !
b1101 $
1"
#30
0"
#31
b1110 !
b1110 $
1"
#32
0"
#33
b1111 !
b1111 $
1"
#34
0"
#35
b10000 !
b10000 $
1"
#36
0"
#37
b10001 !
b10001 $
1"
#38
0"
#39
b10010 !
b10010 $
1"
#40
0"
#41
b10011 !
b10011 $
1"
#42
0"
#43
b10100 !
b10100 $
1"
#44
0"
#45
b10101 !
b10101 $
1"
#46
0"
#47
b10110 !
b10110 $
1"
#48
0"
#49
b10111 !
b10111 $
1"
#50
0"
#51
b11000 !
b11000 $
1"
#52
0"
#53
b11001 !
b11001 $
1"
