encoders/eighttothree/eighttothree.v
module eighttothree(in,out);
 input [7:0]in;
 output reg [2:0]out;
 
 always@(*)
  begin
    if (in == 8'b00000001)
      out = 3'b000;
    else if (in == 8'b00000010)
      out = 3'b001;
    else if (in == 8'b00000100)
      out = 3'b010;
    else if (in == 8'b00001000)
      out = 3'b011;
    else if (in == 8'b00010000)
      out = 3'b100;
    else if (in == 8'b00100000)
      out = 3'b101;
    else if (in == 8'b01000000)
      out = 3'b110;
    else if (in == 8'b10000000)
      out = 3'b111;
    else 
      out = 3'bzzz;    
      
  end
endmodule

encoders/eighttothree/testbench.v
module testbench;
 reg [7:0]in;
 wire [2:0]out;
 
 eighttothree T1 (in,out);
 
 initial
  begin
   $monitor($time,"in=%b,out=%b",in,out);
   $dumpfile("waveform.vcd");
   $dumpvars(0,testbench);
   
   #0 in=8'b00000001;
   #2 in=8'b00000010;
   #2 in=8'b00000100;
   #2 in=8'b00001000;
   #2 in=8'b00010000;
   #2 in=8'b00100000;
   #2 in=8'b01000000;
   #2 in=8'b10000000;
   #2 in=8'b10011100;
   #2 $finish;
  
  end
 endmodule

encoders/eighttothree/waveform.vcd
$date
	Mon Dec 13 23:02:16 2021
$end
$version
	Icarus Verilog
$end
$timescale
	1s
$end
$scope module testbench $end
$var wire 3 ! out [2:0] $end
$var reg 8 " in [7:0] $end
$scope module T1 $end
$var wire 8 # in [7:0] $end
$var reg 3 $ out [2:0] $end
$upscope $end
$upscope $end
$enddefinitions $end
#0
$dumpvars
b0 $
b1 #
b1 "
b0 !
$end
#2
b1 !
b1 $
b10 "
b10 #
#4
b10 !
b10 $
b100 "
b100 #
#6
b11 !
b11 $
b1000 "
b1000 #
#8
b100 !
b100 $
b10000 "
b10000 #
#10
b101 !
b101 $
b100000 "
b100000 #
#12
b110 !
b110 $
b1000000 "
b1000000 #
#14
b111 !
b111 $
b10000000 "
b10000000 #
#16
bz !
bz $
b10011100 "
b10011100 #
