fsm/sequenceDetector/mealy/mealyoverlapping.v
module mealyoverlapping(bitstream,clk,out,reset);
  input bitstream,clk,reset;
  output reg out;
  reg [2:0] NS,PS;
  
  parameter S0=0,S1=1,S2=2,S3=3,S4=4;
  
  
  always@(posedge clk or posedge reset)
   begin
    if(reset) 
     PS <= S0;
    else
     PS <= NS;
   end
   
  always@(PS)
   begin 
    case (PS)
      S0: begin
           $display("i am in s0");
           out = bitstream?0:0;
           NS = bitstream?S1:S0;
           
          end
          
      S1: begin
           $display("i am in s1");
           out = bitstream?0:0;
           NS = bitstream?S2:S0;
           
          end
          
      S2: begin
           $display("i am in s2");
           out = bitstream?0:0;
           NS = bitstream?S2:S3;
          end
     
      S3: begin
           out = bitstream?0:0;
           NS = bitstream?S4:S0;
           $display("i am in s3");
          end
          
      S4: begin
           out = bitstream?1:0;
           NS = bitstream?S2:S0;
           $display("i am in s4");
          end
          
    endcase
 end
endmodule

fsm/sequenceDetector/mealy/testbench.v
module testbench;
 reg bitstream,clk,reset;
 wire out;
 
 mealyoverlapping M1 (bitstream,clk,out,reset);
 
 initial clk=0;
 always clk= #5 ~clk;
 
 initial
  begin
   $monitor($time,"bitstream=%b,clk=%b,reset=%b,out=%b",bitstream,clk,reset,out);
   $dumpfile("waveform.vcd");
   $dumpvars(0,testbench);
   
   #0 reset=1; bitstream=1;
   #2
   #1 reset=0;
   #4 bitstream=1; reset=0;

   #10 bitstream=1;
   #10 bitstream=0;
   #10 bitstream=1;
   #10 bitstream=1;
   #10 bitstream=0;
   #10 bitstream=1;
   #10 bitstream=1;
   #10 $finish;
   
  end
endmodule

fsm/sequenceDetector/mealy/waveform.vcd
$date
	Thu Dec 16 21:56:43 2021
$end
$version
	Icarus Verilog
$end
$timescale
	1s
$end
$scope module testbench $end
$var wire 1 ! out $end
$var reg 1 " bitstream $end
$var reg 1 # clk $end
$var reg 1 $ reset $end
$scope module M1 $end
$var wire 1 " bitstream $end
$var wire 1 # clk $end
$var wire 1 $ reset $end
$var reg 3 % NS [2:0] $end
$var reg 3 & PS [2:0] $end
$var reg 1 ! out $end
$upscope $end
$upscope $end
$enddefinitions $end
#0
$dumpvars
b0 &
b1 %
1$
0#
1"
0!
$end
#3
0$
#5
b10 %
b1 &
1#
#10
0#
#15
b10 &
1#
#20
0#
#25
1#
#27
0"
#30
0#
#35
1#
#37
1"
#40
0#
#45
1#
#50
0#
#55
1#
#57
0"
#60
0#
#65
1#
#67
1"
