1to8Demux/case/oneto8demux.v
module oneto8demux  (a,select,out);
  input a;
  input [2:0]select;
  output [7:0]out;
  reg [7:0]out;
  
  always@(*)
  begin 
    case(select)
    3'b000: out[0] = a;
    3'b001: out[1] = a;
    3'b010: out[2] = a;
    3'b011: out[3] = a;
    3'b100: out[4] = a;
    3'b101: out[5] = a;
    3'b110: out[6] = a;
    3'b111: out[7] = a;
    default: out = 1'bx;
    endcase 
  end
endmodule

1to8Demux/case/testbench.v
module testbench;
  reg A;
  reg [2:0]S;
  wire out;
  
  oneto8demux S1 (A,S,out);
  
  initial 
    begin
      $dumpfile("waveform.vcd");
      $dumpvars(0,testbench);
      $monitor($time,"A=%h,S=%h,out=%b",A,S,out);
      
      #5 A=1; S=3'b000;
      #5 S=3'b001;
      #5 S=3'b010;
      #5 S=3'b011;
      #5 S=3'b100;
      #5 S=3'b101;
      #5 S=3'b110;
      #5 S=3'b111;
      #5 $finish;
    end
endmodule

1to8Demux/case/waveform.vcd
$date
	Fri Sep 24 09:31:08 2021
$end
$version
	Icarus Verilog
$end
$timescale
	1s
$end
$scope module testbench $end
$var wire 1 ! out $end
$var reg 1 " A $end
$var reg 3 # S [2:0] $end
$scope module S1 $end
$var wire 1 " a $end
$var wire 3 $ select [2:0] $end
$var reg 8 % out [7:0] $end
$upscope $end
$upscope $end
$enddefinitions $end
#0
$dumpvars
bx %
bx $
bx #
x"
x!
$end
#5
1!
bx1 %
b0 #
b0 $
1"
#10
bx11 %
b1 #
b1 $
#15
bx111 %
b10 #
b10 $
#20
bx1111 %
b11 #
b11 $
#25
bx11111 %
b100 #
b100 $
#30
bx111111 %
b101 #
b101 $
#35
bx1111111 %
b110 #
b110 $
#40
b11111111 %
b111 #
b111 $
