sequential/t/trial/trytff.v
module trytff(t,e,q);
  input t,e;
  output q;
  reg q;
  
  initial q=0;

  always@(t or e)
    begin 
     if(e & t)
       begin 
         q <= t^q;
       end
     else
       q <= q;
    end
endmodule

sequential/t/trial/testbench.v
module testbench;
     reg t,e;
     wire q;
     
     trytff T1 (t,e,q);
     
     initial 
      begin
      $monitor($time," t=%b,e=%b,q=%b",t,e,q);
      $dumpfile("waveform.vcd");
      $dumpvars(0,testbench);
      
      #5 e=0; t=1;
      #5 e=1;
      #3 t=0;
      #10 t=1;
      #5 t=0;
      #5 t=1;
      #5 t=0;
      #5 $finish;
      
     end
endmodule

sequential/t/trial/waveform.vcd
$date
	Fri Sep 17 11:07:31 2021
$end
$version
	Icarus Verilog
$end
$timescale
	1s
$end
$scope module testbench $end
$var wire 1 ! q $end
$var reg 1 " e $end
$var reg 1 # t $end
$scope module T1 $end
$var wire 1 " e $end
$var wire 1 # t $end
$var reg 1 ! q $end
$upscope $end
$upscope $end
$enddefinitions $end
#0
$dumpvars
x#
x"
0!
$end
#5
1#
0"
#10
1!
1"
#13
0#
#23
0!
1#
#28
0#
#33
1!
1#
#38
0#
