shiftRegister/siso/right/shiftRight/sisorightusingD.v
module dff(d,clk,q);
   input d,clk;
   output q,qbar;
   reg q,qbar;
   
   always@(posedge clk)
     begin
       q <= d;
     end
endmodule


module sisoright (si,clk,so);
   input si,clk;
   output so;
   wire q3,q2,q1;
   
   
   dff D3 (si,clk,q3);
   dff D2 (q3,clk,q2);
   dff D1 (q2,clk,q1);
   dff D0 (q1,clk,so);
   
endmodule

shiftRegister/siso/right/shiftRight/testbench.v
module testbench;
  reg si,clk;
  wire so;
  
  sisoright s1 (si,clk,so);
  
  initial clk=0;
  always clk = #1 ~clk;
  
  initial 
    begin
      $monitor($time,"si=%b,clk=%b,so=%b",si,clk,so);
      $dumpfile("waveform.vcd");
      $dumpvars(0,testbench);
      
      #5 si=1; 
      #5 si=0;
      #5 si=0;
      #5 si=1;
      #10 $finish;
      
   end
endmodule

shiftRegister/siso/right/shiftRight/waveform.vcd
$date
	Tue Dec 14 11:01:48 2021
$end
$version
	Icarus Verilog
$end
$timescale
	1s
$end
$scope module testbench $end
$var wire 1 ! so $end
$var reg 1 " clk $end
$var reg 1 # si $end
$scope module s1 $end
$var wire 1 " clk $end
$var wire 1 # si $end
$var wire 1 ! so $end
$var wire 1 $ q3 $end
$var wire 1 % q2 $end
$var wire 1 & q1 $end
$scope module D0 $end
$var wire 1 " clk $end
$var wire 1 & d $end
$var reg 1 ! q $end
$var reg 1 ' qbar $end
$upscope $end
$scope module D1 $end
$var wire 1 " clk $end
$var wire 1 % d $end
$var reg 1 & q $end
$var reg 1 ( qbar $end
$upscope $end
$scope module D2 $end
$var wire 1 " clk $end
$var wire 1 $ d $end
$var reg 1 % q $end
$var reg 1 ) qbar $end
$upscope $end
$scope module D3 $end
$var wire 1 " clk $end
$var wire 1 # d $end
$var reg 1 $ q $end
$var reg 1 * qbar $end
$upscope $end
$upscope $end
$upscope $end
$enddefinitions $end
#0
$dumpvars
x*
x)
x(
x'
x&
x%
x$
x#
0"
x!
$end
#1
1"
#2
0"
#3
1"
#4
0"
#5
1$
1"
1#
#6
0"
#7
1%
1"
#8
0"
#9
1&
1"
#10
0"
0#
#11
1!
0$
1"
#12
0"
#13
0%
1"
#14
0"
#15
0&
1"
#16
0"
#17
0!
1"
#18
0"
#19
1"
#20
0"
1#
#21
1$
1"
#22
0"
#23
1%
1"
#24
0"
#25
1&
1"
#26
0"
#27
1!
1"
