sequential/jk/jklatch/jklatch.v
module jklatch(j,k,enable,q,qbar);
   input j,k,enable;
   output q,qbar;
   reg q,qbar;
   
   always@(enable or j or k)
     begin 
       if(enable & j==0 & k==0)
         begin 
           q <= q;
           qbar <= qbar;
         end
       else if(enable & j==0 & k==1)
         begin
           q <= 0;
           qbar <= 1;
         end
       else if(enable & j==1 & k==0)
         begin
           q <= 1;
           qbar <= 0;
         end
      else if(enable & j==1 & k==1)
        begin 
          q <=  ~q;
          qbar <= ~qbar;
        end
     end   
endmodule

sequential/jk/jklatch/testbench.v
module testbench;
  reg j,k,enable;
  wire q,qbar;
  
  jklatch J1 (j,k,enable,q,qbar);
  
  initial 
    begin
      $monitor($time," j=%b,k=%b,enable=%b,q=%b,qbar=%b",j,k,enable,q,qbar);
      $dumpfile("waveform.vcd");
      $dumpvars(0,testbench);
      
      #5 enable=0;
      #5 enable=1;
      #2 j=0; k=0;
      #2 j=0; k=1;
      #2 j=1; k=0;
      #2 j=1; k=1;
      #5 $finish;
      
   end
endmodule

sequential/jk/jklatch/waveform.vcd
$date
	Tue Dec 14 23:12:46 2021
$end
$version
	Icarus Verilog
$end
$timescale
	1s
$end
$scope module testbench $end
$var wire 1 ! qbar $end
$var wire 1 " q $end
$var reg 1 # enable $end
$var reg 1 $ j $end
$var reg 1 % k $end
$scope module J1 $end
$var wire 1 # enable $end
$var wire 1 $ j $end
$var wire 1 % k $end
$var reg 1 " q $end
$var reg 1 ! qbar $end
$upscope $end
$upscope $end
$enddefinitions $end
#0
$dumpvars
x%
x$
x#
x"
x!
$end
#5
0#
#10
1#
#12
0%
0$
#14
1!
0"
1%
#16
0!
1"
0%
1$
#18
1%
#19
1!
0"
